ads_throttle/__init__.py
ads_throttle/admin.py
ads_throttle/apps.py
ads_throttle/context_processors.py
ads_throttle/locale/ru/LC_MESSAGES/django.mo
ads_throttle/locale/ru/LC_MESSAGES/django.po
ads_throttle/migrations/0001_initial.py
ads_throttle/migrations/__init__.py
ads_throttle/models.py
ads_throttle/templatetags/__init__.py
ads_throttle/templatetags/ads_throttle_tags.py
ads_throttle/throttling.py
ads_throttle-0.1.3.dist-info/licenses/LICENSE
ads_throttle-0.1.3.dist-info/WHEEL
ads_throttle-0.1.3.dist-info/METADATA
ads_throttle-0.1.3.dist-info/RECORD
