Metadata-Version: 2.4
Name: ads_throttle
Version: 0.1.3
Summary: Django app to mitigate ad network ban risk by throttling suspicious ad impressions.
Author: Artem Frolov
Author-email: Artem Frolov <pypi-username@mail.ru>
License-Expression: MIT
License-File: LICENSE
Classifier: Environment :: Web Environment
Classifier: Framework :: Django
Classifier: Framework :: Django :: 5.2
Classifier: Intended Audience :: Developers
Classifier: License :: OSI Approved :: MIT License
Classifier: Operating System :: OS Independent
Classifier: Programming Language :: Python :: 3.10
Classifier: Programming Language :: Python :: 3.11
Classifier: Programming Language :: Python :: 3.12
Classifier: Programming Language :: Python :: 3.13
Classifier: Programming Language :: Python :: 3.14
Classifier: Topic :: Internet :: WWW/HTTP
Classifier: Topic :: Internet :: WWW/HTTP :: Dynamic Content
Requires-Dist: django>=5.2
Requires-Python: >=3.10
Project-URL: Documentation, https://github.com/frollow/throttle/tree/master/docs
Project-URL: Homepage, https://github.com/frollow/throttle
Project-URL: Issues, https://github.com/frollow/throttle/issues
